[
    {"ID":"#exit","TEXT_ENG":"","TOOLTIP_ENG":"Exit","TEXT_HUN":"","TOOLTIP_HUN":"Kilépés","TEXT_GER":"","TOOLTIP_GER":"Ausfahrt","TEXT_FRA":"","TOOLTIP_FRA":"Sortie","TEXT_ESP":"","TOOLTIP_ESP":"Salida","TEXT_POR":"","TOOLTIP_POR":"SAÍDA","TEXT_RUS":"","TOOLTIP_RUS":"Выход","TEXT_CHN":"","TOOLTIP_CHN":"退出","TEXT_JPN":"","TOOLTIP_JPN":"終了"},
    {"ID":"#components","TEXT_ENG":"MODULES","TOOLTIP_ENG":"","TEXT_HUN":"MODULOK","TOOLTIP_HUN":"","TEXT_GER":"MODULE","TOOLTIP_GER":"","TEXT_FRA":"Modules","TOOLTIP_FRA":"","TEXT_ESP":"Módulos","TOOLTIP_ESP":"","TEXT_POR":"MÓDULOS","TOOLTIP_POR":"","TEXT_RUS":"Модули","TOOLTIP_RUS":"","TEXT_CHN":"模块","TOOLTIP_CHN":"","TEXT_JPN":"モジュール","TOOLTIP_JPN":""},
    {"ID":"#mainSideBarTools","TEXT_ENG":"TOOLS","TOOLTIP_ENG":"","TEXT_HUN":"ESZKÖZÖK","TOOLTIP_HUN":"","TEXT_GER":"WERKZEUGE","TOOLTIP_GER":"","TEXT_FRA":"Outils","TOOLTIP_FRA":"","TEXT_ESP":"Herramientas","TOOLTIP_ESP":"","TEXT_POR":"FERRAMENTAS","TOOLTIP_POR":"","TEXT_RUS":"Инструменты","TOOLTIP_RUS":"","TEXT_CHN":"工具","TOOLTIP_CHN":"","TEXT_JPN":"ツール","TOOLTIP_JPN":""},
    {"ID":"#parana","TEXT_ENG":"PARAMETER ANALYSIS","TOOLTIP_ENG":"Model calibration, and more...","TEXT_HUN":"PARAMÉTERANALÍZIS","TOOLTIP_HUN":"Modell kalibrálás és egyebek...","TEXT_GER":"PARAMETERANALYSE","TOOLTIP_GER":"Modellkalibrierung und mehr...","TEXT_FRA":"ANALYSE DES PARAMÈTRES","TOOLTIP_FRA":"Étalonnage du modèle, et plus encore...","TEXT_ESP":"ANÁLISIS DE PARÁMETROS","TOOLTIP_ESP":"Calibración del modelo, y más...","TEXT_POR":"ANÁLISE DE PARÂMETROS","TOOLTIP_POR":"Calibração de modelos, e mais...","TEXT_RUS":"АНАЛИЗ ПАРАМЕТРОВ","TOOLTIP_RUS":"Калибровка модели, и многое другое...","TEXT_CHN":"参数分析","TOOLTIP_CHN":"模型校准等...","TEXT_JPN":"パラメータ分析","TOOLTIP_JPN":"モデルキャリブレーションなど."},
    {"ID":"#sitegen","TEXT_ENG":"INPUT MANAGER","TOOLTIP_ENG":"Download data from open databases","TEXT_HUN":"BEMENŐ ADAT KEZELŐ","TOOLTIP_HUN":"Adatok letöltése szabad hozzáférésű adatbázisokból","TEXT_GER":"INPUT-MANAGER","TOOLTIP_GER":"Herunterladen von Daten aus offenen Datenbanken","TEXT_FRA":"GESTIONNAIRE D’ENTRÉE","TOOLTIP_FRA":"Télécharger des données à partir de bases de données ouvertes","TEXT_ESP":"GESTOR DE ENTRADA","TOOLTIP_ESP":"Descargar datos de bases de datos abiertas","TEXT_POR":"GESTOR DE ENTRADA","TOOLTIP_POR":"Descarregar dados de bases de dados abertas","TEXT_RUS":"МЕНЕДЖЕР ВВОДА","TOOLTIP_RUS":"Загрузка данных из открытых баз данных","TEXT_CHN":"输入管理器","TOOLTIP_CHN":"从打开的数据库下载数据","TEXT_JPN":"インプットマネージャー","TOOLTIP_JPN":"開いているデータベースからデータをダウンロードする"},
    {"ID":"#calibration","TEXT_ENG":"DATABASE MANAGER","TOOLTIP_ENG":"","TEXT_HUN":"ADATBÁZISKEZELŐ","TOOLTIP_HUN":"","TEXT_GER":"DATABASE-MANAGER","TOOLTIP_GER":"","TEXT_FRA":"GESTIONNAIRE DE BASE DE DONNÉES","TOOLTIP_FRA":"","TEXT_ESP":"ADMINISTRADOR DE BASES DE DATOS","TOOLTIP_ESP":"","TEXT_POR":"GESTOR DE BASE DE DADOs","TOOLTIP_POR":"","TEXT_RUS":"МЕНЕДЖЕР БАЗ ДАННЫХ","TOOLTIP_RUS":"","TEXT_CHN":"数据库管理器","TOOLTIP_CHN":"","TEXT_JPN":"データベース・マネージャー","TOOLTIP_JPN":""},
    {"ID":"#storEditor","TEXT_ENG":"INPUT CREATOR","TOOLTIP_ENG":"","TEXT_HUN":"BEMENŐ ADAT KÉSZÍTŐ","TOOLTIP_HUN":"","TEXT_GER":"","TOOLTIP_GER":"","TEXT_FRA":"","TOOLTIP_FRA":"","TEXT_ESP":"","TOOLTIP_ESP":"","TEXT_POR":"","TOOLTIP_POR":"","TEXT_RUS":"","TOOLTIP_RUS":"","TEXT_CHN":"","TOOLTIP_CHN":"","TEXT_JPN":"","TOOLTIP_JPN":""},
    {"ID":"#mainSideBarLang","TEXT_ENG":"LANGUAGES","TOOLTIP_ENG":"","TEXT_HUN":"NYELVEK","TOOLTIP_HUN":"","TEXT_GER":"SPRACHEN","TOOLTIP_GER":"","TEXT_FRA":"Traduction","TOOLTIP_FRA":"","TEXT_ESP":"Idiomas","TOOLTIP_ESP":"","TEXT_POR":"Idiomas","TOOLTIP_POR":"","TEXT_RUS":"Языки","TOOLTIP_RUS":"","TEXT_CHN":"语言","TOOLTIP_CHN":"","TEXT_JPN":"言語","TOOLTIP_JPN":""},
    {"ID":"#base-huFlag","TEXT_ENG":"","TOOLTIP_ENG":"Magyar változat","TEXT_HUN":"","TOOLTIP_HUN":"Magyar változat","TEXT_GER":"","TOOLTIP_GER":"Magyar változat","TEXT_FRA":"","TOOLTIP_FRA":"Magyar változat","TEXT_ESP":"","TOOLTIP_ESP":"Magyar változat","TEXT_POR":"","TOOLTIP_POR":"Magyar változat","TEXT_RUS":"","TOOLTIP_RUS":"Magyar változat","TEXT_CHN":"","TOOLTIP_CHN":"Magyar változat","TEXT_JPN":"","TOOLTIP_JPN":"Magyar változat"},
    {"ID":"#base-ukFlag","TEXT_ENG":"","TOOLTIP_ENG":"English version","TEXT_HUN":"","TOOLTIP_HUN":"English version","TEXT_GER":"","TOOLTIP_GER":"English version","TEXT_FRA":"","TOOLTIP_FRA":"English version","TEXT_ESP":"","TOOLTIP_ESP":"English version","TEXT_POR":"","TOOLTIP_POR":"English version","TEXT_RUS":"","TOOLTIP_RUS":"English version","TEXT_CHN":"","TOOLTIP_CHN":"English version","TEXT_JPN":"","TOOLTIP_JPN":"English version"},
    {"ID":"#base-gerFlag","TEXT_ENG":"","TOOLTIP_ENG":"Deutsch Version","TEXT_HUN":"","TOOLTIP_HUN":"Deutsch Version","TEXT_GER":"","TOOLTIP_GER":"Deutsch Version","TEXT_FRA":"","TOOLTIP_FRA":"Deutsch Version","TEXT_ESP":"","TOOLTIP_ESP":"Deutsch Version","TEXT_POR":"","TOOLTIP_POR":"Deutsch Version","TEXT_RUS":"","TOOLTIP_RUS":"Deutsch Version","TEXT_CHN":"","TOOLTIP_CHN":"Deutsch Version","TEXT_JPN":"","TOOLTIP_JPN":"Deutsch Version"},
    {"ID":"#base-jpFlag","TEXT_ENG":"","TOOLTIP_ENG":"日本語版","TEXT_HUN":"","TOOLTIP_HUN":"日本語版","TEXT_GER":"","TOOLTIP_GER":"日本語版","TEXT_FRA":"","TOOLTIP_FRA":"日本語版","TEXT_ESP":"","TOOLTIP_ESP":"日本語版","TEXT_POR":"","TOOLTIP_POR":"日本語版","TEXT_RUS":"","TOOLTIP_RUS":"日本語版","TEXT_CHN":"","TOOLTIP_CHN":"日本語版","TEXT_JPN":"","TOOLTIP_JPN":"日本語版"},
    {"ID":"#base-fraFlag","TEXT_ENG":"","TOOLTIP_ENG":"version française","TEXT_HUN":"","TOOLTIP_HUN":"Version française","TEXT_GER":"","TOOLTIP_GER":"Version française","TEXT_FRA":"","TOOLTIP_FRA":"Version française","TEXT_ESP":"","TOOLTIP_ESP":"Version française","TEXT_POR":"","TOOLTIP_POR":"Version française","TEXT_RUS":"","TOOLTIP_RUS":"Version française","TEXT_CHN":"","TOOLTIP_CHN":"Version française","TEXT_JPN":"","TOOLTIP_JPN":"Version française"},
    {"ID":"#base-espFlag","TEXT_ENG":"","TOOLTIP_ENG":"versión en español","TEXT_HUN":"","TOOLTIP_HUN":"Versión en español","TEXT_GER":"","TOOLTIP_GER":"Versión en español","TEXT_FRA":"","TOOLTIP_FRA":"Versión en español","TEXT_ESP":"","TOOLTIP_ESP":"Versión en español","TEXT_POR":"","TOOLTIP_POR":"Versión en español","TEXT_RUS":"","TOOLTIP_RUS":"Versión en español","TEXT_CHN":"","TOOLTIP_CHN":"Versión en español","TEXT_JPN":"","TOOLTIP_JPN":"Versión en español"},
    {"ID":"#base-porFlag","TEXT_ENG":"","TOOLTIP_ENG":"Versão em português","TEXT_HUN":"","TOOLTIP_HUN":"Versão em português","TEXT_GER":"","TOOLTIP_GER":"Versão em português","TEXT_FRA":"","TOOLTIP_FRA":"Versão em português","TEXT_ESP":"","TOOLTIP_ESP":"Versão em português","TEXT_POR":"","TOOLTIP_POR":"Versão em português","TEXT_RUS":"","TOOLTIP_RUS":"Versão em português","TEXT_CHN":"","TOOLTIP_CHN":"Versão em português","TEXT_JPN":"","TOOLTIP_JPN":"Versão em português"},
    {"ID":"#base-rusFlag","TEXT_ENG":"","TOOLTIP_ENG":"Русская версия","TEXT_HUN":"","TOOLTIP_HUN":"Русская версия","TEXT_GER":"","TOOLTIP_GER":"Русская версия","TEXT_FRA":"","TOOLTIP_FRA":"Русская версия","TEXT_ESP":"","TOOLTIP_ESP":"Русская версия","TEXT_POR":"","TOOLTIP_POR":"Русская версия","TEXT_RUS":"","TOOLTIP_RUS":"Русская версия","TEXT_CHN":"","TOOLTIP_CHN":"Русская версия","TEXT_JPN":"","TOOLTIP_JPN":"Русская версия"},
    {"ID":"#base-chiFlag","TEXT_ENG":"","TOOLTIP_ENG":"英文版","TEXT_HUN":"","TOOLTIP_HUN":"英文版","TEXT_GER":"","TOOLTIP_GER":"英文版","TEXT_FRA":"","TOOLTIP_FRA":"英文版","TEXT_ESP":"","TOOLTIP_ESP":"英文版","TEXT_POR":"","TOOLTIP_POR":"英文版","TEXT_RUS":"","TOOLTIP_RUS":"英文版","TEXT_CHN":"","TOOLTIP_CHN":"英文版","TEXT_JPN":"","TOOLTIP_JPN":"英文版"},
    {"ID":"#mainSideBarDirectory","TEXT_ENG":"BASE DIRECTORY","TOOLTIP_ENG":"","TEXT_HUN":"ALAP KÖNYVTÁR","TOOLTIP_HUN":"","TEXT_GER":"HAUPTVERZEICHNIS","TOOLTIP_GER":"","TEXT_FRA":"RÉPERTOIRE PRINCIPAL","TOOLTIP_FRA":"","TEXT_ESP":"DIRECTORIO PRINCIPAL","TOOLTIP_ESP":"","TEXT_POR":"DIRETÓRIO PRINCIPAL","TOOLTIP_POR":"","TEXT_RUS":"ГЛАВНЫЙ КАТАЛОГ","TOOLTIP_RUS":"","TEXT_CHN":"主目录","TOOLTIP_CHN":"","TEXT_JPN":"メインディレクトリ","TOOLTIP_JPN":""},
    {"ID":"#choose","TEXT_ENG":"MODIFY","TOOLTIP_ENG":"","TEXT_HUN":"MÓDOSÍT","TOOLTIP_HUN":"","TEXT_GER":"Ändern","TOOLTIP_GER":"","TEXT_FRA":"Modifier","TOOLTIP_FRA":"","TEXT_ESP":"Modificar","TOOLTIP_ESP":"","TEXT_POR":"MODIFICAR","TOOLTIP_POR":"","TEXT_RUS":"Изменить","TOOLTIP_RUS":"","TEXT_CHN":"修改","TOOLTIP_CHN":"","TEXT_JPN":"変更","TOOLTIP_JPN":""},
    {"ID":"#site","TEXT_ENG":"","TOOLTIP_ENG":"Plot level simulations","TEXT_HUN":"","TOOLTIP_HUN":"Parcella szintű szimulációk","TEXT_GER":"","TOOLTIP_GER":"Simulationen auf Plotebene","TEXT_FRA":"","TOOLTIP_FRA":"Simulations de niveau de parcelle","TEXT_ESP":"","TOOLTIP_ESP":"Simulaciones de nivel de trazado","TEXT_POR":"","TOOLTIP_POR":"Simulações de nível de enredo","TEXT_RUS":"","TOOLTIP_RUS":"Моделирование уровня участка","TEXT_CHN":"","TOOLTIP_CHN":"绘图级别模拟","TEXT_JPN":"","TOOLTIP_JPN":"プロット レベル シミュレーション"},
    {"ID":"#show","TEXT_ENG":"","TOOLTIP_ENG":"Plot creator","TEXT_HUN":"","TOOLTIP_HUN":"Grafikon készítő","TEXT_GER":"","TOOLTIP_GER":"Plot-Ersteller","TEXT_FRA":"","TOOLTIP_FRA":"Créateur de l’intrigue","TEXT_ESP":"","TOOLTIP_ESP":"Creador de trazados","TEXT_POR":"","TOOLTIP_POR":"Criador de enredo","TEXT_RUS":"","TOOLTIP_RUS":"Создатель участка","TEXT_CHN":"","TOOLTIP_CHN":"绘图创建者","TEXT_JPN":"","TOOLTIP_JPN":"プロット作成者"},
    {"ID":"#grid","TEXT_ENG":"","TOOLTIP_ENG":"Grid level simulations","TEXT_HUN":"","TOOLTIP_HUN":"Régió szintű szimulációk","TEXT_GER":"","TOOLTIP_GER":"Grid-Level-Simulationen","TEXT_FRA":"","TOOLTIP_FRA":"Simulations au niveau de la grille","TEXT_ESP":"","TOOLTIP_ESP":"Simulaciones de nivel de cuadrícula","TEXT_POR":"","TOOLTIP_POR":"Simulações de nível de grelha","TEXT_RUS":"","TOOLTIP_RUS":"Моделирование уровня сетки","TEXT_CHN":"","TOOLTIP_CHN":"网格级模拟","TEXT_JPN":"","TOOLTIP_JPN":"グリッド レベルシミュレーション"},
    {"ID":"#map","TEXT_ENG":"","TOOLTIP_ENG":"Map creator","TEXT_HUN":"","TOOLTIP_HUN":"Térkép készítő","TEXT_GER":"","TOOLTIP_GER":"Kartenersteller","TEXT_FRA":"","TOOLTIP_FRA":"Créateur de carte","TEXT_ESP":"","TOOLTIP_ESP":"Creador de mapas","TEXT_POR":"","TOOLTIP_POR":"Criador de mapas","TEXT_RUS":"","TOOLTIP_RUS":"Создатель карты","TEXT_CHN":"","TOOLTIP_CHN":"地图创建者","TEXT_JPN":"","TOOLTIP_JPN":"マップ作成者"},
    {"ID":"#sitediv-refresh","TEXT_ENG":"","TOOLTIP_ENG":"Refresh content of the dropdown menus based on the file list of the corresponding folders","TEXT_HUN":"","TOOLTIP_HUN":"Frissítse a legördülő menük tartalmát a megfelelő mappák fájllistája alapján","TEXT_GER":"","TOOLTIP_GER":"Aktualisieren des Inhalts der Dropdownmenüs basierend auf der Dateiliste der entsprechenden Ordner","TEXT_FRA":"","TOOLTIP_FRA":"Actualiser le contenu des menus déroulants en fonction de la liste de fichiers des dossiers correspondants","TEXT_ESP":"","TOOLTIP_ESP":"Actualizar el contenido de los menús desplegables en función de la lista de archivos de las carpetas correspondientes","TEXT_POR":"","TOOLTIP_POR":"Atualizar o conteúdo dos menus suspensos com base na lista de ficheiros das pastas correspondentes","TEXT_RUS":"","TOOLTIP_RUS":"Обновление содержимого меню выпадения на основе списка файлов соответствующих папок","TEXT_CHN":"","TOOLTIP_CHN":"根据相应文件夹的文件列表刷新下拉菜单的内容","TEXT_JPN":"","TOOLTIP_JPN":"対応するフォルダのファイル リストに基づいてドロップダウン メニューの内容を更新する"},
    {"ID":"#manModuls","TEXT_ENG":"management options:","TOOLTIP_ENG":"","TEXT_HUN":"agrotechnikai műveletek:","TOOLTIP_HUN":"","TEXT_GER":"Management-Optionen:","TOOLTIP_GER":"","TEXT_FRA":"options de gestion :","TOOLTIP_FRA":"","TEXT_ESP":"opciones de gestión:","TOOLTIP_ESP":"","TEXT_POR":"opções de gestão:","TOOLTIP_POR":"","TEXT_RUS":"варианты управления:","TOOLTIP_RUS":"","TEXT_CHN":"管理选项：","TOOLTIP_CHN":"","TEXT_JPN":"管理オプション:","TOOLTIP_JPN":""},
    {"ID":"#shiftIn","TEXT_ENG":"shift in ...","TOOLTIP_ENG":"","TEXT_HUN":"ezek módosítása ...","TOOLTIP_HUN":"","TEXT_GER":"Verschiebung in ...","TOOLTIP_GER":"","TEXT_FRA":"changement dans ...","TOOLTIP_FRA":"","TEXT_ESP":"cambio en ...","TOOLTIP_ESP":"","TEXT_POR":"mudança em ...","TOOLTIP_POR":"","TEXT_RUS":"сдвиг в ...","TOOLTIP_RUS":"","TEXT_CHN":"换班...","TOOLTIP_CHN":"","TEXT_JPN":"でシフト.","TOOLTIP_JPN":""},
    {"ID":"#sitediv-iniFile_container label","TEXT_ENG":"INI file:","TOOLTIP_ENG":"","TEXT_HUN":"INI fájl:","TOOLTIP_HUN":"","TEXT_GER":"INI-Datei:","TOOLTIP_GER":"","TEXT_FRA":"Fichier INI :","TOOLTIP_FRA":"","TEXT_ESP":"Archivo INI:","TOOLTIP_ESP":"","TEXT_POR":"Ficheiro INI:","TOOLTIP_POR":"","TEXT_RUS":"ФАЙЛ INI:","TOOLTIP_RUS":"","TEXT_CHN":"INI 文件：","TOOLTIP_CHN":"","TEXT_JPN":"INI ファイル:","TOOLTIP_JPN":""},
    {"ID":"#sitediv-weatherFile_container label","TEXT_ENG":"WEATHER file:","TOOLTIP_ENG":"","TEXT_HUN":"IDŐJÁRÁS fájl:","TOOLTIP_HUN":"","TEXT_GER":"WETTER-Datei:","TOOLTIP_GER":"","TEXT_FRA":"Fichier MÉTÉO :","TOOLTIP_FRA":"","TEXT_ESP":"Archivo WEATHER:","TOOLTIP_ESP":"","TEXT_POR":"Ficheiro WEATHER:","TOOLTIP_POR":"","TEXT_RUS":"Файл WEATHER:","TOOLTIP_RUS":"","TEXT_CHN":"天气文件：","TOOLTIP_CHN":"","TEXT_JPN":"天気ファイル:","TOOLTIP_JPN":""},
    {"ID":"#sitediv-soilFile_container label","TEXT_ENG":"SOIL file:","TOOLTIP_ENG":"","TEXT_HUN":"TALAJ fájl:","TOOLTIP_HUN":"","TEXT_GER":"SOIL-Datei:","TOOLTIP_GER":"","TEXT_FRA":"Fichier SOIL :","TOOLTIP_FRA":"","TEXT_ESP":"Archivo SOIL:","TOOLTIP_ESP":"","TEXT_POR":"Ficheiro SOLO:","TOOLTIP_POR":"","TEXT_RUS":"Файл SOIL:","TOOLTIP_RUS":"","TEXT_CHN":"土壤文件：","TOOLTIP_CHN":"","TEXT_JPN":"土壌ファイル:","TOOLTIP_JPN":""},
    {"ID":"#sitediv-managementFile_container label","TEXT_ENG":"MANAGEMENT file:","TOOLTIP_ENG":"","TEXT_HUN":"AGROTECHNIKA fájl:","TOOLTIP_HUN":"","TEXT_GER":"MANAGEMENT-Datei:","TOOLTIP_GER":"","TEXT_FRA":"Fichier GESTION :","TOOLTIP_FRA":"","TEXT_ESP":"Archivo MANAGEMENT:","TOOLTIP_ESP":"","TEXT_POR":"Ficheiro MANAGEMENT:","TOOLTIP_POR":"","TEXT_RUS":"Файл MANAGEMENT:","TOOLTIP_RUS":"","TEXT_CHN":"管理文件：","TOOLTIP_CHN":"","TEXT_JPN":"管理ファイル:","TOOLTIP_JPN":""},
    {"ID":"#sitediv-planting_container label","TEXT_ENG":"planting:","TOOLTIP_ENG":"","TEXT_HUN":"vetés:","TOOLTIP_HUN":"","TEXT_GER":"Pflanzen:","TOOLTIP_GER":"","TEXT_FRA":"Plantation:","TOOLTIP_FRA":"","TEXT_ESP":"Plantar:","TOOLTIP_ESP":"","TEXT_POR":"Plantação:","TOOLTIP_POR":"","TEXT_RUS":"Посадки:","TOOLTIP_RUS":"","TEXT_CHN":"种植：","TOOLTIP_CHN":"","TEXT_JPN":"植栽：","TOOLTIP_JPN":""},
    {"ID":"#sitediv-harvest_container label","TEXT_ENG":"harvest:","TOOLTIP_ENG":"","TEXT_HUN":"aratás:","TOOLTIP_HUN":"","TEXT_GER":"Ernte:","TOOLTIP_GER":"","TEXT_FRA":"Récolte:","TOOLTIP_FRA":"","TEXT_ESP":"Cosecha:","TOOLTIP_ESP":"","TEXT_POR":"Colheita:","TOOLTIP_POR":"","TEXT_RUS":"Урожай:","TOOLTIP_RUS":"","TEXT_CHN":"收获：","TOOLTIP_CHN":"","TEXT_JPN":"収穫：","TOOLTIP_JPN":""},
    {"ID":"#sitediv-fertilization_container label","TEXT_ENG":"fertilization:","TOOLTIP_ENG":"","TEXT_HUN":"műtrágyázás:","TOOLTIP_HUN":"","TEXT_GER":"Befruchtung:","TOOLTIP_GER":"","TEXT_FRA":"Fertilisation:","TOOLTIP_FRA":"","TEXT_ESP":"Fertilización:","TOOLTIP_ESP":"","TEXT_POR":"fertilização:","TOOLTIP_POR":"","TEXT_RUS":"Оплодотворения:","TOOLTIP_RUS":"","TEXT_CHN":"施肥：","TOOLTIP_CHN":"","TEXT_JPN":"受精：","TOOLTIP_JPN":""},
    {"ID":"#sitediv-irrigation_container label","TEXT_ENG":"irrigation:","TOOLTIP_ENG":"","TEXT_HUN":"öntözés:","TOOLTIP_HUN":"","TEXT_GER":"Bewässerung:","TOOLTIP_GER":"","TEXT_FRA":"Irrigation:","TOOLTIP_FRA":"","TEXT_ESP":"Riego:","TOOLTIP_ESP":"","TEXT_POR":"irrigação:","TOOLTIP_POR":"","TEXT_RUS":"Орошения:","TOOLTIP_RUS":"","TEXT_CHN":"灌溉：","TOOLTIP_CHN":"","TEXT_JPN":"灌漑：","TOOLTIP_JPN":""},
    {"ID":"#sitediv-cultivation_container label","TEXT_ENG":"cultivation:","TOOLTIP_ENG":"","TEXT_HUN":"talajművelés:","TOOLTIP_HUN":"","TEXT_GER":"Anbau:","TOOLTIP_GER":"","TEXT_FRA":"Culture:","TOOLTIP_FRA":"","TEXT_ESP":"Cultivo:","TOOLTIP_ESP":"","TEXT_POR":"cultivo:","TOOLTIP_POR":"","TEXT_RUS":"Выращивания:","TOOLTIP_RUS":"","TEXT_CHN":"培养：","TOOLTIP_CHN":"","TEXT_JPN":"栽培：","TOOLTIP_JPN":""},
    {"ID":"#sitediv-grazing_container label","TEXT_ENG":"grazing:","TOOLTIP_ENG":"","TEXT_HUN":"legeltetés:","TOOLTIP_HUN":"","TEXT_GER":"Weiden:","TOOLTIP_GER":"","TEXT_FRA":"Pâturage:","TOOLTIP_FRA":"","TEXT_ESP":"Pastoreo:","TOOLTIP_ESP":"","TEXT_POR":"pastoreio:","TOOLTIP_POR":"","TEXT_RUS":"Выпаса:","TOOLTIP_RUS":"","TEXT_CHN":"放牧：","TOOLTIP_CHN":"","TEXT_JPN":"放牧：","TOOLTIP_JPN":""},
    {"ID":"#sitediv-mowing_container label","TEXT_ENG":"mowing:","TOOLTIP_ENG":"","TEXT_HUN":"kaszálás:","TOOLTIP_HUN":"","TEXT_GER":"Mähen:","TOOLTIP_GER":"","TEXT_FRA":"Fauchage:","TOOLTIP_FRA":"","TEXT_ESP":"Siega:","TOOLTIP_ESP":"","TEXT_POR":"Corte:","TOOLTIP_POR":"","TEXT_RUS":"Скашивания:","TOOLTIP_RUS":"","TEXT_CHN":"修剪：","TOOLTIP_CHN":"","TEXT_JPN":"刈り取り：","TOOLTIP_JPN":""},
    {"ID":"#sitediv-thinning_container label","TEXT_ENG":"thinning:","TOOLTIP_ENG":"","TEXT_HUN":"ritkítás:","TOOLTIP_HUN":"","TEXT_GER":"Ausdünnung:","TOOLTIP_GER":"","TEXT_FRA":"Amincissement:","TOOLTIP_FRA":"","TEXT_ESP":"Adelgazamiento:","TOOLTIP_ESP":"","TEXT_POR":"desbaste:","TOOLTIP_POR":"","TEXT_RUS":"Истончение:","TOOLTIP_RUS":"","TEXT_CHN":"细化：","TOOLTIP_CHN":"","TEXT_JPN":"間伐：","TOOLTIP_JPN":""},
    {"ID":"#outputid-label","TEXT_ENG":"OUTPUT DATA TABLE:","TOOLTIP_ENG":"","TEXT_HUN":"KIMENŐADAT TÁBLA:","TOOLTIP_HUN":"","TEXT_GER":"AUSGABEDATENTABELLE:","TOOLTIP_GER":"","TEXT_FRA":"TABLEAU DES DONNÉES DE SORTIE :","TOOLTIP_FRA":"","TEXT_ESP":"TABLA DE DATOS DE SALIDA:","TOOLTIP_ESP":"","TEXT_POR":"TABELA DE DADOS DE SAÍDA:","TOOLTIP_POR":"","TEXT_RUS":"ТАБЛИЦА ВЫВОДНЫХ ДАННЫХ:","TOOLTIP_RUS":"","TEXT_CHN":"输出数据表：","TOOLTIP_CHN":"","TEXT_JPN":"出力データ テーブル:","TOOLTIP_JPN":""},
    {"ID":"#sitediv-popRun-runModel","TEXT_ENG":"START SIMULATION","TOOLTIP_ENG":"","TEXT_HUN":"SZIMULÁCIÓ INDÍTÁSA","TOOLTIP_HUN":"","TEXT_GER":"START SIMULATION","TOOLTIP_GER":"","TEXT_FRA":"SIMULATION DE DÉMARRAGE","TOOLTIP_FRA":"","TEXT_ESP":"INICIAR SIMULACIÓN","TOOLTIP_ESP":"","TEXT_POR":"SIMULAÇÃO DE INÍCIO","TOOLTIP_POR":"","TEXT_RUS":"НАЧАЛО МОДЕЛИРОВАНИЯ","TOOLTIP_RUS":"","TEXT_CHN":"开始模拟","TOOLTIP_CHN":"","TEXT_JPN":"シミュレーションを開始する","TOOLTIP_JPN":""},
    {"ID":"#sitediv-Show","TEXT_ENG":"PLOT","TOOLTIP_ENG":"Create plots using simulation results","TEXT_HUN":"EREDMÉNYEK ÁBRÁZOLÁSA","TOOLTIP_HUN":"Parcella létrehozása a szimuláció eredményei alapján","TEXT_GER":"Plot","TOOLTIP_GER":"Erstellen von Diagrammen mithilfe von Simulationsergebnissen","TEXT_FRA":"Intrigue","TOOLTIP_FRA":"Créer des parcelles à l’aide de résultats de simulation","TEXT_ESP":"conspirar","TOOLTIP_ESP":"Crear trazados utilizando resultados de simulación","TEXT_POR":"ENREDO","TOOLTIP_POR":"Criar enredos usando resultados de simulação","TEXT_RUS":"Печати","TOOLTIP_RUS":"Создание участков с использованием результатов моделирования","TEXT_CHN":"情节","TOOLTIP_CHN":"使用模拟结果创建绘图","TEXT_JPN":"プロット","TOOLTIP_JPN":"シミュレーション結果を使用してプロットを作成する"},
    {"ID":"#sitediv-planshift_date_container label","TEXT_ENG":"date (day):","TOOLTIP_ENG":"","TEXT_HUN":"dátum (nap):","TOOLTIP_HUN":"","TEXT_GER":"Datum (Tag):","TOOLTIP_GER":"","TEXT_FRA":"date (jour):","TOOLTIP_FRA":"","TEXT_ESP":"fecha (día):","TOOLTIP_ESP":"","TEXT_POR":"data (dia):","TOOLTIP_POR":"","TEXT_RUS":"дата (день):","TOOLTIP_RUS":"","TEXT_CHN":"日期（天）：","TOOLTIP_CHN":"","TEXT_JPN":"日付(日):","TOOLTIP_JPN":""},
    {"ID":"#sitediv-harvshift_date_container label","TEXT_ENG":"date (day):","TOOLTIP_ENG":"","TEXT_HUN":"dátum (nap):","TOOLTIP_HUN":"","TEXT_GER":"Datum (Tag):","TOOLTIP_GER":"","TEXT_FRA":"date (jour):","TOOLTIP_FRA":"","TEXT_ESP":"fecha (día):","TOOLTIP_ESP":"","TEXT_POR":"data (dia):","TOOLTIP_POR":"","TEXT_RUS":"дата (день):","TOOLTIP_RUS":"","TEXT_CHN":"日期（天）：","TOOLTIP_CHN":"","TEXT_JPN":"日付(日):","TOOLTIP_JPN":""},
    {"ID":"#sitediv-fertshift_date_container label","TEXT_ENG":"date (day):","TOOLTIP_ENG":"","TEXT_HUN":"dátum (nap):","TOOLTIP_HUN":"","TEXT_GER":"Datum (Tag):","TOOLTIP_GER":"","TEXT_FRA":"date (jour):","TOOLTIP_FRA":"","TEXT_ESP":"fecha (día):","TOOLTIP_ESP":"","TEXT_POR":"data (dia):","TOOLTIP_POR":"","TEXT_RUS":"дата (день):","TOOLTIP_RUS":"","TEXT_CHN":"日期（天）：","TOOLTIP_CHN":"","TEXT_JPN":"日付(日):","TOOLTIP_JPN":""},
    {"ID":"#sitediv-irrshift_date_container label","TEXT_ENG":"date (day):","TOOLTIP_ENG":"","TEXT_HUN":"dátum (nap):","TOOLTIP_HUN":"","TEXT_GER":"Datum (Tag):","TOOLTIP_GER":"","TEXT_FRA":"date (jour):","TOOLTIP_FRA":"","TEXT_ESP":"fecha (día):","TOOLTIP_ESP":"","TEXT_POR":"data (dia):","TOOLTIP_POR":"","TEXT_RUS":"дата (день):","TOOLTIP_RUS":"","TEXT_CHN":"日期（天）：","TOOLTIP_CHN":"","TEXT_JPN":"日付(日):","TOOLTIP_JPN":""},
    {"ID":"#sitediv-planshift_density_container label","TEXT_ENG":"density (p/m²):","TOOLTIP_ENG":"","TEXT_HUN":"sűrűség (p/m²):","TOOLTIP_HUN":"","TEXT_GER":"Dichte (p/m²):","TOOLTIP_GER":"","TEXT_FRA":"densité (p/m²):","TOOLTIP_FRA":"","TEXT_ESP":"densidad (p/m²):","TOOLTIP_ESP":"","TEXT_POR":"densidade (p/m²):","TOOLTIP_POR":"","TEXT_RUS":"плотность (p/m²):","TOOLTIP_RUS":"","TEXT_CHN":"密度（p/m²):","TOOLTIP_CHN":"","TEXT_JPN":"密度(p/m²):","TOOLTIP_JPN":""},
    {"ID":"#sitediv-fertshift_amount_container label","TEXT_ENG":"amount (kg/ha):","TOOLTIP_ENG":"","TEXT_HUN":"mennyiség (kg/ha):","TOOLTIP_HUN":"","TEXT_GER":"Menge (kg/ha):","TOOLTIP_GER":"","TEXT_FRA":"quantité (kg/ha):","TOOLTIP_FRA":"","TEXT_ESP":"cantidad (kg/ha):","TOOLTIP_ESP":"","TEXT_POR":"quantidade (kg/ha):","TOOLTIP_POR":"","TEXT_RUS":"количество (кг/га):","TOOLTIP_RUS":"","TEXT_CHN":"数量（公斤/公顷）：","TOOLTIP_CHN":"","TEXT_JPN":"量(kg /ha):","TOOLTIP_JPN":""},
    {"ID":"#sitediv-irrshift_amount_container label","TEXT_ENG":"amount (mm):","TOOLTIP_ENG":"","TEXT_HUN":"mennyiség (mm):","TOOLTIP_HUN":"","TEXT_GER":"Menge (mm):","TOOLTIP_GER":"","TEXT_FRA":"quantité (mm):","TOOLTIP_FRA":"","TEXT_ESP":"cantidad (mm):","TOOLTIP_ESP":"","TEXT_POR":"montante (mm):","TOOLTIP_POR":"","TEXT_RUS":"количество (мм):","TOOLTIP_RUS":"","TEXT_CHN":"数量（毫米）：","TOOLTIP_CHN":"","TEXT_JPN":"金額 (mm):","TOOLTIP_JPN":""},
    {"ID":"#observations","TEXT_ENG":"OBSERVATIONS:","TOOLTIP_ENG":"","TEXT_HUN":"MEGFIGYELÉSEK","TOOLTIP_HUN":"","TEXT_GER":"BEOBACHTUNGEN:","TOOLTIP_GER":"","TEXT_FRA":"OBSERVATIONS:","TOOLTIP_FRA":"","TEXT_ESP":"Observaciones:","TOOLTIP_ESP":"","TEXT_POR":"OBSERVAÇÕES:","TOOLTIP_POR":"","TEXT_RUS":"Наблюдения:","TOOLTIP_RUS":"","TEXT_CHN":"观察：","TOOLTIP_CHN":"","TEXT_JPN":"観測：","TOOLTIP_JPN":""},
    {"ID":"#simres","TEXT_ENG":"SIMULATION RESULTS:","TOOLTIP_ENG":"","TEXT_HUN":"SZIMULÁCIÓ EREDMÉNYEK:","TOOLTIP_HUN":"","TEXT_GER":"SIMULATIONSERGEBNISSE:","TOOLTIP_GER":"","TEXT_FRA":"RÉSULTATS DE LA SIMULATION :","TOOLTIP_FRA":"","TEXT_ESP":"RESULTADOS DE SIMULACIONES:","TOOLTIP_ESP":"","TEXT_POR":"RESULTADOS DA SIMULAÇÃO:","TOOLTIP_POR":"","TEXT_RUS":"РЕЗУЛЬТАТЫ МОДЕЛИРОВАНИЯ:","TOOLTIP_RUS":"","TEXT_CHN":"模拟结果：","TOOLTIP_CHN":"","TEXT_JPN":"シミュレーション結果:","TOOLTIP_JPN":""},
    {"ID":"#createplot","TEXT_ENG":"CREATE PLOT WITH:","TOOLTIP_ENG":"","TEXT_HUN":"PARCELLA LÉTREHOZÁS EZZEL:","TOOLTIP_HUN":"","TEXT_GER":"PLOT ERSTELLEN MIT:","TOOLTIP_GER":"","TEXT_FRA":"CRÉEZ UNE PARCELLE AVEC :","TOOLTIP_FRA":"","TEXT_ESP":"CREAR PARCELA CON:","TOOLTIP_ESP":"","TEXT_POR":"CRIAR ENREDO COM:","TOOLTIP_POR":"","TEXT_RUS":"СОЗДАЙТЕ СЮЖЕТ С ПОМОЩЬЮ:","TOOLTIP_RUS":"","TEXT_CHN":"使用：","TOOLTIP_CHN":"","TEXT_JPN":"次の方法でプロットを作成します。","TOOLTIP_JPN":""},
    {"ID":"#showdiv-experimentID_container label","TEXT_ENG":"data file:","TOOLTIP_ENG":"","TEXT_HUN":"adat fájl:","TOOLTIP_HUN":"","TEXT_GER":"","TOOLTIP_GER":"","TEXT_FRA":"","TOOLTIP_FRA":"","TEXT_ESP":"","TOOLTIP_ESP":"","TEXT_POR":"","TOOLTIP_POR":"","TEXT_RUS":"","TOOLTIP_RUS":"","TEXT_CHN":"","TOOLTIP_CHN":"","TEXT_JPN":"","TOOLTIP_JPN":""},
    {"ID":"#showdiv-alias_container label","TEXT_ENG":"alias:","TOOLTIP_ENG":"","TEXT_HUN":"alias:","TOOLTIP_HUN":"","TEXT_GER":"Alias:","TOOLTIP_GER":"","TEXT_FRA":"Alias:","TOOLTIP_FRA":"","TEXT_ESP":"Alias:","TOOLTIP_ESP":"","TEXT_POR":"pseudónimo:","TOOLTIP_POR":"","TEXT_RUS":"Псевдоним:","TOOLTIP_RUS":"","TEXT_CHN":"别名：","TOOLTIP_CHN":"","TEXT_JPN":"エイリアス：","TOOLTIP_JPN":""},
    {"ID":"#showdiv-del","TEXT_ENG":"DELETE SELECTED","TOOLTIP_ENG":"Delet selected simulation results from the list","TEXT_HUN":"KIVÁLASZTOTTAK TÖRLÉSE","TOOLTIP_HUN":"Kiválasztott szimuláció eredmények törlése a listából","TEXT_GER":"DELETE AUSGEWÄHLT","TOOLTIP_GER":"Ausgewählte Simulationsergebnisse aus der Liste delet","TEXT_FRA":"SUPPRIMER SÉLECTIONNÉ","TOOLTIP_FRA":"Delet résultats de simulation sélectionnés à partir de la liste","TEXT_ESP":"ELIMINAR SELECCIONADO","TOOLTIP_ESP":"Delet resultados de simulación seleccionados de la lista","TEXT_POR":"EXCLUIR SELECIONADO","TOOLTIP_POR":"Delet resultados de simulação selecionados da lista","TEXT_RUS":"УДАЛЕНИЕ ВЫБРАНО","TOOLTIP_RUS":"Удаление выбранных результатов моделирования из списка","TEXT_CHN":"删除已选择","TOOLTIP_CHN":"从列表中删除选定的模拟结果","TEXT_JPN":"選択した削除","TOOLTIP_JPN":"選択したシミュレーション結果をリストから削除します"},
    {"ID":"#showdiv-export","TEXT_ENG":"EXPORT","TOOLTIP_ENG":"Export plot data into an Excel file","TEXT_HUN":"EXPORT","TOOLTIP_HUN":"Parcella adatok exportálása egy Excel fájlba","TEXT_GER":"Exportieren","TOOLTIP_GER":"Exportieren von Plotdaten in eine Excel-Datei","TEXT_FRA":"Exportation","TOOLTIP_FRA":"Exporter des données de parcelle dans un fichier Excel","TEXT_ESP":"exportar","TOOLTIP_ESP":"Exportar datos de trazado a un archivo de Excel","TEXT_POR":"EXPORTAÇÃO","TOOLTIP_POR":"Exportar dados de enredo num ficheiro Excel","TEXT_RUS":"Экспорт","TOOLTIP_RUS":"Экспорт данных участка в файл Excel","TEXT_CHN":"出口","TOOLTIP_CHN":"将绘图数据导出到 Excel 文件中","TEXT_JPN":"エクスポート","TOOLTIP_JPN":"Excel ファイルへの印刷データのエクスポート"},
    {"ID":"#showdiv-show","TEXT_ENG":"CREATE PLOT","TOOLTIP_ENG":"","TEXT_HUN":"ÁBRA LÉTREHOZÁSA","TOOLTIP_HUN":"","TEXT_GER":"PLOT ERSTELLEN","TOOLTIP_GER":"","TEXT_FRA":"CRÉER UNE PARCELLE","TOOLTIP_FRA":"","TEXT_ESP":"CREAR PARCELA","TOOLTIP_ESP":"","TEXT_POR":"CRIAR ENREDO","TOOLTIP_POR":"","TEXT_RUS":"СОЗДАТЬ СЮЖЕТ","TOOLTIP_RUS":"","TEXT_CHN":"创建绘图","TOOLTIP_CHN":"","TEXT_JPN":"プロットを作成する","TOOLTIP_JPN":""},
    {"ID":"#showdiv-varset_container label","TEXT_ENG":"filter to:","TOOLTIP_ENG":"","TEXT_HUN":"szűrés:","TOOLTIP_HUN":"","TEXT_GER":"Filter auf:","TOOLTIP_GER":"","TEXT_FRA":"filtrer pour :","TOOLTIP_FRA":"","TEXT_ESP":"filtro para:","TOOLTIP_ESP":"","TEXT_POR":"filtro para:","TOOLTIP_POR":"","TEXT_RUS":"фильтр для:","TOOLTIP_RUS":"","TEXT_CHN":"筛选器到：","TOOLTIP_CHN":"","TEXT_JPN":"フィルタの適用範囲:","TOOLTIP_JPN":""},
    {"ID":"#colone","TEXT_ENG":"VARIABLE","TOOLTIP_ENG":"","TEXT_HUN":"VÁLTOZÓ","TOOLTIP_HUN":"","TEXT_GER":"","TOOLTIP_GER":"","TEXT_FRA":"","TOOLTIP_FRA":"","TEXT_ESP":"","TOOLTIP_ESP":"","TEXT_POR":"","TOOLTIP_POR":"","TEXT_RUS":"","TOOLTIP_RUS":"","TEXT_CHN":"","TOOLTIP_CHN":"","TEXT_JPN":"","TOOLTIP_JPN":""},
    {"ID":"#coltwo","TEXT_ENG":"T-STEP","TOOLTIP_ENG":"","TEXT_HUN":"LÉPTÉK","TOOLTIP_HUN":"","TEXT_GER":"","TOOLTIP_GER":"","TEXT_FRA":"","TOOLTIP_FRA":"","TEXT_ESP":"","TOOLTIP_ESP":"","TEXT_POR":"","TOOLTIP_POR":"","TEXT_RUS":"","TOOLTIP_RUS":"","TEXT_CHN":"","TOOLTIP_CHN":"","TEXT_JPN":"","TOOLTIP_JPN":""},
    {"ID":"#colthree","TEXT_ENG":"FUNC","TOOLTIP_ENG":"","TEXT_HUN":"FÜGV","TOOLTIP_HUN":"","TEXT_GER":"","TOOLTIP_GER":"","TEXT_FRA":"","TOOLTIP_FRA":"","TEXT_ESP":"","TOOLTIP_ESP":"","TEXT_POR":"","TOOLTIP_POR":"","TEXT_RUS":"","TOOLTIP_RUS":"","TEXT_CHN":"","TOOLTIP_CHN":"","TEXT_JPN":"","TOOLTIP_JPN":""},
    {"ID":"#colfour","TEXT_ENG":"PLOT TYPE","TOOLTIP_ENG":"","TEXT_HUN":"TÍPUS","TOOLTIP_HUN":"","TEXT_GER":"","TOOLTIP_GER":"","TEXT_FRA":"","TOOLTIP_FRA":"","TEXT_ESP":"","TOOLTIP_ESP":"","TEXT_POR":"","TOOLTIP_POR":"","TEXT_RUS":"","TOOLTIP_RUS":"","TEXT_CHN":"","TOOLTIP_CHN":"","TEXT_JPN":"","TOOLTIP_JPN":""}
]